.DS_Store
class_namespaces/.DS_Store
class_namespaces/__init__.py
class_namespaces/descriptor_inspector.py
class_namespaces/flags.py
class_namespaces/inspector.py
class_namespaces/namespaces.py
class_namespaces/ops.py
class_namespaces/proxy.py
class_namespaces/scope_proxy.py
class_namespaces/compat/__init__.py
class_namespaces/compat/abc.py
class_namespaces-0.6.3.dist-info/DESCRIPTION.rst
class_namespaces-0.6.3.dist-info/METADATA
class_namespaces-0.6.3.dist-info/RECORD
class_namespaces-0.6.3.dist-info/WHEEL
class_namespaces-0.6.3.dist-info/metadata.json
class_namespaces-0.6.3.dist-info/top_level.txt
