Metadata-Version: 2.0
Name: class-namespaces
Version: 0.6.3
Summary: Class Namespaces
Home-page: https://github.com/mwchase/class-namespaces
Author: Max Woerner Chase
Author-email: max.chase@gmail.com
License: MIT
Keywords: class namespaces
Platform: UNKNOWN
Classifier: Development Status :: 3 - Alpha
Classifier: Intended Audience :: Developers
Classifier: Topic :: Software Development :: Libraries
Classifier: License :: OSI Approved :: MIT License
Classifier: Programming Language :: Python :: 3
Classifier: Programming Language :: Python :: 3.3
Classifier: Programming Language :: Python :: 3.4
Classifier: Programming Language :: Python :: 3.5
Provides-Extra: test
Requires-Dist: coverage; extra == 'test'
Requires-Dist: pytest; extra == 'test'
